xcauto/__init__.py
xcauto/derv.py
xcauto/functionals/__init__.py
xcauto/functionals/becke.py
xcauto/functionals/lyp.py
xcauto/functionals/pbe.py
xcauto/functionals/slater.py
xcauto/functionals/utils.py
xcauto/functionals/vwn.py
xcauto-0.2.0.dist-info/LICENSE
xcauto-0.2.0.dist-info/WHEEL
xcauto-0.2.0.dist-info/METADATA
xcauto-0.2.0.dist-info/RECORD
