Metadata-Version: 2.1
Name: xcauto
Version: 0.2.0
Summary: xcauto: Arbitrary order exchange-correlation functional derivatives using JAX.
Home-page: https://github.com/dftlibs/xcauto
License: UNKNOWN
Author: Radovan Bast
Author-email: radovan.bast@uit.no
Classifier: License :: OSI Approved :: Mozilla Public License 2.0 (MPL 2.0)
Requires-Dist: jax
Requires-Dist: jaxlib
Requires-Dist: black ; extra == "dev"
Requires-Dist: pytest ; extra == "test"
Provides-Extra: dev
Provides-Extra: test
